asyncgnostic/__init__.py
asyncgnostic-0.2.0.dist-info/LICENSE
asyncgnostic-0.2.0.dist-info/METADATA
asyncgnostic-0.2.0.dist-info/WHEEL
asyncgnostic-0.2.0.dist-info/RECORD
