Metadata-Version: 2.3
Name: asyncgnostic
Version: 0.2.0
Summary: Python functions agnostic towards being called with await or otherwise.
License: MIT
Author: Harshad Sharma
Author-email: harshad@sharma.io
Requires-Python: >=3.9,<4.0
Classifier: License :: OSI Approved :: MIT License
Classifier: Programming Language :: Python :: 3
Classifier: Programming Language :: Python :: 3.9
Classifier: Programming Language :: Python :: 3.10
Classifier: Programming Language :: Python :: 3.11
Classifier: Programming Language :: Python :: 3.12
Classifier: Programming Language :: Python :: 3.13
